env_yaml/__init__.py
env_yaml/loader.py
env_yaml-0.0.3.dist-info/METADATA
env_yaml-0.0.3.dist-info/WHEEL
env_yaml-0.0.3.dist-info/top_level.txt
env_yaml-0.0.3.dist-info/RECORD
