Metadata-Version: 2.1
Name: env-yaml
Version: 0.0.3
Summary: Provides a yaml loader which substitutes environment variables and supports defaults
Home-page: https://github.com/iamKunal/env-yaml-python
Author: Kunal Gupta
Provides-Extra: test
